easydb/__init__.py
easydb/flat.py
easydb/pda.py
python_data_access-1.3.1.dist-info/METADATA
python_data_access-1.3.1.dist-info/WHEEL
python_data_access-1.3.1.dist-info/top_level.txt
python_data_access-1.3.1.dist-info/RECORD
