Metadata-Version: 2.1
Name: python-data-access
Version: 1.3.1
Summary: Lightweight and fast database access layer with query builder for MySQL and SQLite databases
Home-page: https://github.com/expandmade-tb/python-data-access
Author: tbednarek
Author-email: thomas.bednarek@expandmade.com
License: MIT
Platform: UNKNOWN
Classifier: Development Status :: 4 - Beta
Classifier: Intended Audience :: Developers
Classifier: License :: OSI Approved :: MIT License
Classifier: Operating System :: POSIX :: Linux
Classifier: Programming Language :: Python :: 3.10
Requires-Dist: mysql.connector
